modelscan/__init__.py
modelscan/_version.py
modelscan/cli.py
modelscan/error.py
modelscan/issues.py
modelscan/middlewares/__init__.py
modelscan/middlewares/format_via_extension.py
modelscan/middlewares/middleware.py
modelscan/model.py
modelscan/modelscan.py
modelscan/reports.py
modelscan/scanners/__init__.py
modelscan/scanners/h5/__init__.py
modelscan/scanners/h5/scan.py
modelscan/scanners/keras/__init__.py
modelscan/scanners/keras/scan.py
modelscan/scanners/pickle/__init__.py
modelscan/scanners/pickle/scan.py
modelscan/scanners/saved_model/__init__.py
modelscan/scanners/saved_model/scan.py
modelscan/scanners/scan.py
modelscan/settings.py
modelscan/skip.py
modelscan/tools/LICENSE
modelscan/tools/cli_utils.py
modelscan/tools/picklescanner.py
modelscan/tools/utils.py
modelscan-0.8.7.dist-info/LICENSE
modelscan-0.8.7.dist-info/METADATA
modelscan-0.8.7.dist-info/WHEEL
modelscan-0.8.7.dist-info/entry_points.txt
modelscan-0.8.7.dist-info/RECORD
