Metadata-Version: 2.3
Name: modelscan
Version: 0.8.7
Summary: The modelscan package is a cli tool for detecting unsafe operations in model files across various model serialization formats.
License: Apache-2.0
Author: ProtectAI
Author-email: community@protectai.com
Requires-Python: >=3.10,<3.13
Classifier: License :: OSI Approved :: Apache Software License
Classifier: Programming Language :: Python :: 3
Classifier: Programming Language :: Python :: 3.10
Classifier: Programming Language :: Python :: 3.11
Classifier: Programming Language :: Python :: 3.12
Provides-Extra: h5py
Provides-Extra: tensorflow
Requires-Dist: click (>=8.1.3,<9.0.0)
Requires-Dist: h5py (>=3.9.0,<4.0.0) ; extra == "h5py"
Requires-Dist: numpy (>=1.24.3)
Requires-Dist: rich (>=13.4.2,<15.0.0)
Requires-Dist: setuptools (==80.9.0)
Requires-Dist: tensorflow (>=2.17,<3.0) ; extra == "tensorflow"
Requires-Dist: tomlkit (>=0.12.3,<0.14.0)
